{"AAPL":{"entity":"Apple Inc.","cik":"0000320193","asof":"2026-03-28","basis":"TTM","epsTTM":8.26,"bvps":7.250522,"de":0.776723,"roe":1.151036,"npm":0.271519,"cr":1.070357,"revG":0.165952,"epsG":0.218182},"TSLA":{"entity":"Tesla, Inc.","cik":"0001318605","asof":"2026-03-31","basis":"TTM","epsTTM":1.09,"bvps":22.396748,"de":0.007709,"roe":0.045913,"npm":0.039457,"cr":2.043119,"revG":0.157848,"epsG":0.083333},"NVDA":{"entity":"NVIDIA CORP","cik":"0001045810","asof":"2026-04-26","basis":"TTM","epsTTM":6.53,"bvps":8.077438,"de":0.043331,"roe":0.816543,"npm":5.930482,"cr":3.440776,"revG":0.408163,"epsG":2.144737},"CMCSA":{"entity":"Comcast Corporation","cik":"0001166691","asof":"2026-03-31","basis":"TTM","epsTTM":5.1,"bvps":42.787625,"de":0.061105,"roe":0.212939,"npm":0.150044,"cr":0.865318,"revG":0.052531,"epsG":-0.325843},"MSFT":{"entity":"MICROSOFT CORPORATION","cik":"0000789019","asof":"2026-03-31","basis":"TTM","epsTTM":16.79,"bvps":55.7812,"de":0.097165,"roe":0.302186,"npm":0.393423,"cr":1.282948,"revG":0.18297,"epsG":0.234104},"GOOGL":{"entity":"Alphabet Inc.","cik":"0001652044","asof":"2026-03-31","basis":"TTM","epsTTM":13.11,"bvps":39.513536,"de":0.166057,"roe":0.334641,"npm":0.445377,"cr":1.922447,"revG":0.120376,"epsG":0.818505},"AMZN":{"entity":"AMAZON COM INC","cik":"0001018724","asof":"2026-03-31","basis":"FY","epsTTM":8.36,"bvps":41.08111,"de":0.275859,"roe":0.205465,"npm":0.122241,"cr":1.177153,"revG":0.166072,"epsG":0.748428},"META":{"entity":"Meta Platforms, Inc.","cik":"0001326801","asof":"2026-03-31","basis":"TTM","epsTTM":27.5,"de":0.241086,"roe":0.28967,"npm":0.328368,"cr":2.347764,"revG":0.330789,"epsG":0.623639},"AMD":{"entity":"ADVANCED MICRO DEVICES INC","cik":"0000002488","asof":"2026-03-28","basis":"TTM","epsTTM":3.05,"bvps":39.532672,"de":0.050014,"roe":0.077705,"npm":0.133737,"cr":2.724919,"revG":0.378462,"epsG":0.909091},"INTC":{"entity":"INTEL CORP","cik":"0000050863","asof":"2026-03-28","basis":"TTM","epsTTM":-0.6,"bvps":22.16355,"de":0.408693,"roe":-0.028493,"npm":-0.059037,"cr":2.311958,"revG":0.07184,"epsG":-2.842105},"QCOM":{"entity":"QUALCOMM INC/DE","cik":"0000804328","asof":"2026-03-29","basis":"TTM","epsTTM":9.3,"bvps":4.657495,"de":3.017111,"roe":2.021593,"npm":0.223081,"cr":2.366336,"revG":-0.034612,"epsG":1.730159},"CSCO":{"entity":"CISCO SYSTEMS, INC.","cik":"0000858877","asof":"2026-04-25","basis":"TTM","epsTTM":1.33,"bvps":12.396755,"de":0.468042,"roe":0.244735,"npm":0.196852,"cr":0.924585,"revG":0.119584},"ORCL":{"entity":"Oracle Corporation","cik":"0001341439","asof":"2026-02-28","basis":"TTM","epsTTM":5.57,"bvps":13.384696,"de":0.188882,"roe":0.421094,"npm":0.252981,"cr":1.347031,"revG":0.216561,"epsG":0.245098},"IBM":{"entity":"INTERNATIONAL BUSINESS MACHINES CORP","cik":"0000051143","asof":"2026-03-31","basis":"TTM","epsTTM":11.33,"bvps":35.083005,"de":1.906138,"roe":0.326136,"npm":0.156056,"cr":0.795841,"revG":0.094629,"epsG":0.142857},"WMT":{"entity":"WALMART INC.","cik":"0000104169","asof":"2026-04-30","basis":"TTM","bvps":11.853363,"de":0.432344,"roe":0.241026,"npm":0.031661,"cr":0.771441,"revG":0.071368},"COST":{"entity":"COSTCO WHOLESALE CORP /NEW","cik":"0000909832","asof":"2026-05-10","basis":"TTM","epsTTM":2.92,"bvps":75.559417,"de":0.169208,"roe":0.26375,"npm":0.030104,"cr":1.072451,"revG":0.115845,"epsG":0.416667},"KO":{"entity":"COCA COLA CO","cik":"0000021344","asof":"2026-04-03","basis":"TTM","bvps":7.817115,"de":1.085125,"roe":0.407368,"npm":0.278001,"cr":1.35803,"revG":0.120676,"epsG":0.442623},"PEP":{"entity":"PepsiCo, Inc.","cik":"0000077476","asof":"2026-03-21","basis":"TTM","bvps":15.644934,"de":2.025955,"roe":0.408409,"npm":0.091494,"cr":0.896714,"revG":0.085049},"PG":{"entity":"PROCTER & GAMBLE CO","cik":"0000080424","asof":"2026-03-31","basis":"TTM","epsTTM":6.84,"bvps":23.503832,"de":0.534048,"roe":0.303612,"npm":0.191623,"cr":0.731973,"revG":0.073776,"epsG":0.058442},"MCD":{"entity":"McDONALD’S CORPORATION","cik":"0000063908","asof":"2026-03-31","basis":"TTM","epsTTM":12.13,"npm":0.316185,"cr":1.135794,"revG":0.094191,"epsG":0.069231},"NKE":{"entity":"NIKE, Inc.","cik":"0000320187","asof":"2026-02-28","basis":"TTM","epsTTM":1.52,"bvps":16.472758,"de":0.569837,"roe":0.159688,"npm":0.048363,"cr":2.13914,"revG":0.000887,"epsG":-0.351852},"DIS":{"entity":"WALT DISNEY CO/","cik":"0001744489","asof":"2026-03-28","basis":"TTM","epsTTM":6.25,"bvps":62.601373,"de":0.435644,"roe":0.103249,"npm":0.115398,"cr":0.679099,"revG":0.065493,"epsG":-0.298343},"SBUX":{"entity":"Starbucks Corporation","cik":"0000829224","asof":"2026-03-29","basis":"TTM","npm":0.038875,"cr":0.922249,"revG":0.087872,"epsG":0.35},"JPM":{"entity":"JPMORGAN CHASE & CO","cik":"0000019617","asof":"2026-03-31","basis":"TTM","epsTTM":20.89,"bvps":135.859843,"de":0.741486,"roe":0.161794,"npm":0.322828,"revG":0.048839,"epsG":0.171598},"BAC":{"entity":"BANK OF AMERICA CORP /DE/","cik":"0000070858","asof":"2026-03-31","basis":"TTM","epsTTM":4.02,"bvps":42.36795,"de":1.084133,"roe":0.105422,"npm":0.273243,"revG":0.10619,"epsG":0.233333},"V":{"entity":"VISA INC.","cik":"0001403161","asof":"2026-03-31","basis":"TTM","bvps":56.335136,"de":0.906911,"roe":0.841094,"npm":0.516792,"cr":1.087667,"revG":0.170523},"MA":{"entity":"Mastercard Inc","cik":"0001141391","asof":"2025-12-31","basis":"FY","epsTTM":17.28,"bvps":54.835464,"de":2.821848,"roe":2.227712,"npm":0.436792,"cr":0.980989,"revG":0.171352,"epsG":0.211699},"JNJ":{"entity":"Johnson & Johnson","cik":"0000200406","asof":"2026-03-29","basis":"TTM","epsTTM":8.63,"bvps":33.726083,"de":0.48687,"roe":0.259158,"npm":0.218343,"cr":1.025244,"revG":0.099073,"epsG":-0.528634},"UNH":{"entity":"UnitedHealth Group Incorporated","cik":"0000731766","asof":"2026-03-31","basis":"TTM","epsTTM":13.28,"bvps":36.359856,"de":2.273168,"roe":0.364749,"npm":0.026782,"cr":0.798491,"revG":0.019585,"epsG":0.007299},"PFE":{"entity":"Pfizer Inc.","cik":"0000078003","asof":"2026-03-29","basis":"TTM","epsTTM":1.31,"bvps":15.808735,"de":0.715042,"roe":0.08314,"npm":0.14713,"cr":1.24671,"revG":-0.06043,"epsG":-0.096154},"CAT":{"entity":"CATERPILLAR INC","cik":"0000018230","asof":"2025-12-31","basis":"FY","epsTTM":20.08,"bvps":40.509119,"de":1.645016,"roe":0.476099,"npm":0.12556,"cr":1.352794,"revG":0.222191,"epsG":0.302381},"BA":{"entity":"THE BOEING COMPANY","cik":"0000012927","asof":"2026-03-31","basis":"TTM","epsTTM":2.53,"bvps":7.594802,"de":8.320862,"roe":0.378821,"npm":0.029624,"cr":1.176168,"epsG":0.3125},"XOM":{"entity":"Exxon Mobil Corporation","cik":"0000034088","asof":"2026-03-31","basis":"TTM","epsTTM":5.94,"bvps":61.371349,"de":0.115182,"roe":0.099512,"npm":0.104546,"cr":1.036121,"revG":-0.273851,"epsG":-0.431818},"CVX":{"entity":"Chevron Corp","cik":"0000093410","asof":"2026-03-31","basis":"TTM","epsTTM":5.74,"bvps":92.245034,"de":0.175266,"roe":0.059924,"npm":0.059224,"cr":1.094461,"revG":0.031561,"epsG":-0.445},"T":{"entity":"AT&T INC.","cik":"0000732717","asof":"2026-03-31","basis":"TTM","epsTTM":2.97,"bvps":18.078997,"de":0.507622,"roe":0.170603,"cr":0.917911,"epsG":-0.114754},"VZ":{"entity":"VERIZON COMMUNICATIONS INC","cik":"0000732712","asof":"2026-03-31","basis":"TTM","epsTTM":4.11,"bvps":25.055807,"de":1.12679,"roe":0.16574,"npm":0.124617,"cr":0.639997,"revG":0.02852,"epsG":0.043478}}
